[
    {
        "courseId": "012728",
        "courseOfferNumber": 1,
        "termCode": "1251",
        "termName": "Winter 2025",
        "associatedAcademicCareer": "GRD",
        "associatedAcademicGroupCode": "ART",
        "associatedAcademicOrgCode": "ANTH",
        "subjectCode": "ANTH",
        "catalogNumber": "614",
        "title": "Research Methods",
        "descriptionAbbreviated": "Research Methods",
        "description": "An examination of the methods of qualitative research, including participant observation and unstructured interviews, as well as the ethical considerations of fieldwork. Other topics, such as comparative and historical methods, may be included. [Note: Department Consent required]",
        "gradingBasis": "NUM",
        "courseComponentCode": "LEC",
        "enrollConsentCode": "D",
        "enrollConsentDescription": "No Consent Required",
        "dropConsentCode": "N",
        "dropConsentDescription": "No Consent Required",
        "requirementsDescription": null
    },
    {
        "courseId": "012737",
        "courseOfferNumber": 1,
        "termCode": "1251",
        "termName": "Winter 2025",
        "associatedAcademicCareer": "GRD",
        "associatedAcademicGroupCode": "ART",
        "associatedAcademicOrgCode": "ANTH",
        "subjectCode": "ANTH",
        "catalogNumber": "660",
        "title": "Reading Course",
        "descriptionAbbreviated": "Reading Course",
        "description": "A program of directed reading, complemented with the writing of papers or participation in research.  Reading courses are arranged by students through their advisors or advisory committees and must be approved by the graduate chair of the department.  This course may be repeated provided different content is involved.",
        "gradingBasis": "NUM",
        "courseComponentCode": "RDG",
        "enrollConsentCode": "D",
        "enrollConsentDescription": "No Consent Required",
        "dropConsentCode": "N",
        "dropConsentDescription": "No Consent Required",
        "requirementsDescription": null
    }
]